{
  "num_frames": 50,
  "note": "frame_index_1based is the 1-based index used in prompts and model outputs for this frame pool.",
  "frames": [
    {
      "frame_index_1based": 1,
      "timestamp_sec": 161.6116116116116,
      "original_frame_index": 0,
      "image_relpath": "sampled_frames/sample_001_ts_161.61s.jpg"
    },
    {
      "frame_index_1based": 2,
      "timestamp_sec": 161.97864531197865,
      "original_frame_index": 22,
      "image_relpath": "sampled_frames/sample_002_ts_161.98s.jpg"
    },
    {
      "frame_index_1based": 3,
      "timestamp_sec": 162.36236236236235,
      "original_frame_index": 45,
      "image_relpath": "sampled_frames/sample_003_ts_162.36s.jpg"
    },
    {
      "frame_index_1based": 4,
      "timestamp_sec": 162.7293960627294,
      "original_frame_index": 67,
      "image_relpath": "sampled_frames/sample_004_ts_162.73s.jpg"
    },
    {
      "frame_index_1based": 5,
      "timestamp_sec": 163.11311311311312,
      "original_frame_index": 90,
      "image_relpath": "sampled_frames/sample_005_ts_163.11s.jpg"
    },
    {
      "frame_index_1based": 6,
      "timestamp_sec": 163.48014681348013,
      "original_frame_index": 112,
      "image_relpath": "sampled_frames/sample_006_ts_163.48s.jpg"
    },
    {
      "frame_index_1based": 7,
      "timestamp_sec": 163.86386386386386,
      "original_frame_index": 135,
      "image_relpath": "sampled_frames/sample_007_ts_163.86s.jpg"
    },
    {
      "frame_index_1based": 8,
      "timestamp_sec": 164.2308975642309,
      "original_frame_index": 157,
      "image_relpath": "sampled_frames/sample_008_ts_164.23s.jpg"
    },
    {
      "frame_index_1based": 9,
      "timestamp_sec": 164.61461461461462,
      "original_frame_index": 180,
      "image_relpath": "sampled_frames/sample_009_ts_164.61s.jpg"
    },
    {
      "frame_index_1based": 10,
      "timestamp_sec": 164.98164831498164,
      "original_frame_index": 202,
      "image_relpath": "sampled_frames/sample_010_ts_164.98s.jpg"
    },
    {
      "frame_index_1based": 11,
      "timestamp_sec": 165.3486820153487,
      "original_frame_index": 224,
      "image_relpath": "sampled_frames/sample_011_ts_165.35s.jpg"
    },
    {
      "frame_index_1based": 12,
      "timestamp_sec": 165.7323990657324,
      "original_frame_index": 247,
      "image_relpath": "sampled_frames/sample_012_ts_165.73s.jpg"
    },
    {
      "frame_index_1based": 13,
      "timestamp_sec": 166.09943276609943,
      "original_frame_index": 269,
      "image_relpath": "sampled_frames/sample_013_ts_166.10s.jpg"
    },
    {
      "frame_index_1based": 14,
      "timestamp_sec": 166.48314981648315,
      "original_frame_index": 292,
      "image_relpath": "sampled_frames/sample_014_ts_166.48s.jpg"
    },
    {
      "frame_index_1based": 15,
      "timestamp_sec": 166.85018351685017,
      "original_frame_index": 314,
      "image_relpath": "sampled_frames/sample_015_ts_166.85s.jpg"
    },
    {
      "frame_index_1based": 16,
      "timestamp_sec": 167.2339005672339,
      "original_frame_index": 337,
      "image_relpath": "sampled_frames/sample_016_ts_167.23s.jpg"
    },
    {
      "frame_index_1based": 17,
      "timestamp_sec": 167.60093426760093,
      "original_frame_index": 359,
      "image_relpath": "sampled_frames/sample_017_ts_167.60s.jpg"
    },
    {
      "frame_index_1based": 18,
      "timestamp_sec": 167.98465131798466,
      "original_frame_index": 382,
      "image_relpath": "sampled_frames/sample_018_ts_167.98s.jpg"
    },
    {
      "frame_index_1based": 19,
      "timestamp_sec": 168.35168501835167,
      "original_frame_index": 404,
      "image_relpath": "sampled_frames/sample_019_ts_168.35s.jpg"
    },
    {
      "frame_index_1based": 20,
      "timestamp_sec": 168.7354020687354,
      "original_frame_index": 427,
      "image_relpath": "sampled_frames/sample_020_ts_168.74s.jpg"
    },
    {
      "frame_index_1based": 21,
      "timestamp_sec": 169.10243576910244,
      "original_frame_index": 449,
      "image_relpath": "sampled_frames/sample_021_ts_169.10s.jpg"
    },
    {
      "frame_index_1based": 22,
      "timestamp_sec": 169.46946946946946,
      "original_frame_index": 471,
      "image_relpath": "sampled_frames/sample_022_ts_169.47s.jpg"
    },
    {
      "frame_index_1based": 23,
      "timestamp_sec": 169.85318651985318,
      "original_frame_index": 494,
      "image_relpath": "sampled_frames/sample_023_ts_169.85s.jpg"
    },
    {
      "frame_index_1based": 24,
      "timestamp_sec": 170.22022022022023,
      "original_frame_index": 516,
      "image_relpath": "sampled_frames/sample_024_ts_170.22s.jpg"
    },
    {
      "frame_index_1based": 25,
      "timestamp_sec": 170.60393727060392,
      "original_frame_index": 539,
      "image_relpath": "sampled_frames/sample_025_ts_170.60s.jpg"
    },
    {
      "frame_index_1based": 26,
      "timestamp_sec": 170.97097097097097,
      "original_frame_index": 561,
      "image_relpath": "sampled_frames/sample_026_ts_170.97s.jpg"
    },
    {
      "frame_index_1based": 27,
      "timestamp_sec": 171.3546880213547,
      "original_frame_index": 584,
      "image_relpath": "sampled_frames/sample_027_ts_171.35s.jpg"
    },
    {
      "frame_index_1based": 28,
      "timestamp_sec": 171.7217217217217,
      "original_frame_index": 606,
      "image_relpath": "sampled_frames/sample_028_ts_171.72s.jpg"
    },
    {
      "frame_index_1based": 29,
      "timestamp_sec": 172.10543877210543,
      "original_frame_index": 629,
      "image_relpath": "sampled_frames/sample_029_ts_172.11s.jpg"
    },
    {
      "frame_index_1based": 30,
      "timestamp_sec": 172.47247247247248,
      "original_frame_index": 651,
      "image_relpath": "sampled_frames/sample_030_ts_172.47s.jpg"
    },
    {
      "frame_index_1based": 31,
      "timestamp_sec": 172.8395061728395,
      "original_frame_index": 673,
      "image_relpath": "sampled_frames/sample_031_ts_172.84s.jpg"
    },
    {
      "frame_index_1based": 32,
      "timestamp_sec": 173.22322322322321,
      "original_frame_index": 696,
      "image_relpath": "sampled_frames/sample_032_ts_173.22s.jpg"
    },
    {
      "frame_index_1based": 33,
      "timestamp_sec": 173.59025692359026,
      "original_frame_index": 718,
      "image_relpath": "sampled_frames/sample_033_ts_173.59s.jpg"
    },
    {
      "frame_index_1based": 34,
      "timestamp_sec": 173.97397397397398,
      "original_frame_index": 741,
      "image_relpath": "sampled_frames/sample_034_ts_173.97s.jpg"
    },
    {
      "frame_index_1based": 35,
      "timestamp_sec": 174.341007674341,
      "original_frame_index": 763,
      "image_relpath": "sampled_frames/sample_035_ts_174.34s.jpg"
    },
    {
      "frame_index_1based": 36,
      "timestamp_sec": 174.72472472472472,
      "original_frame_index": 786,
      "image_relpath": "sampled_frames/sample_036_ts_174.72s.jpg"
    },
    {
      "frame_index_1based": 37,
      "timestamp_sec": 175.09175842509177,
      "original_frame_index": 808,
      "image_relpath": "sampled_frames/sample_037_ts_175.09s.jpg"
    },
    {
      "frame_index_1based": 38,
      "timestamp_sec": 175.47547547547546,
      "original_frame_index": 831,
      "image_relpath": "sampled_frames/sample_038_ts_175.48s.jpg"
    },
    {
      "frame_index_1based": 39,
      "timestamp_sec": 175.8425091758425,
      "original_frame_index": 853,
      "image_relpath": "sampled_frames/sample_039_ts_175.84s.jpg"
    },
    {
      "frame_index_1based": 40,
      "timestamp_sec": 176.22622622622623,
      "original_frame_index": 876,
      "image_relpath": "sampled_frames/sample_040_ts_176.23s.jpg"
    },
    {
      "frame_index_1based": 41,
      "timestamp_sec": 176.59325992659325,
      "original_frame_index": 898,
      "image_relpath": "sampled_frames/sample_041_ts_176.59s.jpg"
    },
    {
      "frame_index_1based": 42,
      "timestamp_sec": 176.9602936269603,
      "original_frame_index": 920,
      "image_relpath": "sampled_frames/sample_042_ts_176.96s.jpg"
    },
    {
      "frame_index_1based": 43,
      "timestamp_sec": 177.34401067734402,
      "original_frame_index": 943,
      "image_relpath": "sampled_frames/sample_043_ts_177.34s.jpg"
    },
    {
      "frame_index_1based": 44,
      "timestamp_sec": 177.71104437771103,
      "original_frame_index": 965,
      "image_relpath": "sampled_frames/sample_044_ts_177.71s.jpg"
    },
    {
      "frame_index_1based": 45,
      "timestamp_sec": 178.09476142809476,
      "original_frame_index": 988,
      "image_relpath": "sampled_frames/sample_045_ts_178.09s.jpg"
    },
    {
      "frame_index_1based": 46,
      "timestamp_sec": 178.4617951284618,
      "original_frame_index": 1010,
      "image_relpath": "sampled_frames/sample_046_ts_178.46s.jpg"
    },
    {
      "frame_index_1based": 47,
      "timestamp_sec": 178.84551217884552,
      "original_frame_index": 1033,
      "image_relpath": "sampled_frames/sample_047_ts_178.85s.jpg"
    },
    {
      "frame_index_1based": 48,
      "timestamp_sec": 179.21254587921254,
      "original_frame_index": 1055,
      "image_relpath": "sampled_frames/sample_048_ts_179.21s.jpg"
    },
    {
      "frame_index_1based": 49,
      "timestamp_sec": 179.59626292959626,
      "original_frame_index": 1078,
      "image_relpath": "sampled_frames/sample_049_ts_179.60s.jpg"
    },
    {
      "frame_index_1based": 50,
      "timestamp_sec": 179.96329662996328,
      "original_frame_index": 1100,
      "image_relpath": "sampled_frames/sample_050_ts_179.96s.jpg"
    }
  ]
}